{
    "repo": {
        "repository_url": "https://github.com/mapol-chem/qed-ci",
        "branch": "direct_ci",
        "commit": "7f25d1c5fd458a06002e79d610aa17399f213f71"
    },
    "molecule": {
        "molecule_name": "LiH",
        "geometry": [],
        "symbols": [
            "Li",
            "H"
        ],
        "z-matrix": [
            "\n    0 1\n    Li\n    H 1 1.4\n    symmetry c1\n",
            "\n    0 1\n    Li\n    H 1 1.4163265306122448\n    symmetry c1\n",
            "\n    0 1\n    Li\n    H 1 1.4326530612244897\n    symmetry c1\n",
            "\n    0 1\n    Li\n    H 1 1.4489795918367345\n    symmetry c1\n",
            "\n    0 1\n    Li\n    H 1 1.4653061224489796\n    symmetry c1\n",
            "\n    0 1\n    Li\n    H 1 1.4816326530612245\n    symmetry c1\n",
            "\n    0 1\n    Li\n    H 1 1.4979591836734694\n    symmetry c1\n",
            "\n    0 1\n    Li\n    H 1 1.5142857142857142\n    symmetry c1\n",
            "\n    0 1\n    Li\n    H 1 1.530612244897959\n    symmetry c1\n",
            "\n    0 1\n    Li\n    H 1 1.546938775510204\n    symmetry c1\n",
            "\n    0 1\n    Li\n    H 1 1.5632653061224488\n    symmetry c1\n",
            "\n    0 1\n    Li\n    H 1 1.5795918367346937\n    symmetry c1\n",
            "\n    0 1\n    Li\n    H 1 1.5959183673469388\n    symmetry c1\n",
            "\n    0 1\n    Li\n    H 1 1.6122448979591837\n    symmetry c1\n",
            "\n    0 1\n    Li\n    H 1 1.6285714285714286\n    symmetry c1\n",
            "\n    0 1\n    Li\n    H 1 1.6448979591836734\n    symmetry c1\n",
            "\n    0 1\n    Li\n    H 1 1.6612244897959183\n    symmetry c1\n",
            "\n    0 1\n    Li\n    H 1 1.6775510204081634\n    symmetry c1\n",
            "\n    0 1\n    Li\n    H 1 1.693877551020408\n    symmetry c1\n",
            "\n    0 1\n    Li\n    H 1 1.7102040816326531\n    symmetry c1\n",
            "\n    0 1\n    Li\n    H 1 1.726530612244898\n    symmetry c1\n",
            "\n    0 1\n    Li\n    H 1 1.7428571428571429\n    symmetry c1\n",
            "\n    0 1\n    Li\n    H 1 1.7591836734693878\n    symmetry c1\n",
            "\n    0 1\n    Li\n    H 1 1.7755102040816326\n    symmetry c1\n",
            "\n    0 1\n    Li\n    H 1 1.7918367346938777\n    symmetry c1\n",
            "\n    0 1\n    Li\n    H 1 1.8081632653061224\n    symmetry c1\n",
            "\n    0 1\n    Li\n    H 1 1.8244897959183675\n    symmetry c1\n",
            "\n    0 1\n    Li\n    H 1 1.8408163265306123\n    symmetry c1\n",
            "\n    0 1\n    Li\n    H 1 1.8571428571428572\n    symmetry c1\n",
            "\n    0 1\n    Li\n    H 1 1.873469387755102\n    symmetry c1\n",
            "\n    0 1\n    Li\n    H 1 1.889795918367347\n    symmetry c1\n",
            "\n    0 1\n    Li\n    H 1 1.906122448979592\n    symmetry c1\n",
            "\n    0 1\n    Li\n    H 1 1.9224489795918367\n    symmetry c1\n",
            "\n    0 1\n    Li\n    H 1 1.9387755102040818\n    symmetry c1\n",
            "\n    0 1\n    Li\n    H 1 1.9551020408163267\n    symmetry c1\n",
            "\n    0 1\n    Li\n    H 1 1.9714285714285715\n    symmetry c1\n",
            "\n    0 1\n    Li\n    H 1 1.9877551020408164\n    symmetry c1\n",
            "\n    0 1\n    Li\n    H 1 2.0040816326530613\n    symmetry c1\n",
            "\n    0 1\n    Li\n    H 1 2.0204081632653064\n    symmetry c1\n",
            "\n    0 1\n    Li\n    H 1 2.036734693877551\n    symmetry c1\n",
            "\n    0 1\n    Li\n    H 1 2.053061224489796\n    symmetry c1\n",
            "\n    0 1\n    Li\n    H 1 2.069387755102041\n    symmetry c1\n",
            "\n    0 1\n    Li\n    H 1 2.085714285714286\n    symmetry c1\n",
            "\n    0 1\n    Li\n    H 1 2.1020408163265305\n    symmetry c1\n",
            "\n    0 1\n    Li\n    H 1 2.1183673469387756\n    symmetry c1\n",
            "\n    0 1\n    Li\n    H 1 2.1346938775510207\n    symmetry c1\n",
            "\n    0 1\n    Li\n    H 1 2.1510204081632653\n    symmetry c1\n",
            "\n    0 1\n    Li\n    H 1 2.1673469387755104\n    symmetry c1\n",
            "\n    0 1\n    Li\n    H 1 2.183673469387755\n    symmetry c1\n",
            "\n    0 1\n    Li\n    H 1 2.2\n    symmetry c1\n"
        ],
        "bond_length": [
            1.4,
            1.4163265306122448,
            1.4326530612244897,
            1.4489795918367345,
            1.4653061224489796,
            1.4816326530612245,
            1.4979591836734694,
            1.5142857142857142,
            1.530612244897959,
            1.546938775510204,
            1.5632653061224488,
            1.5795918367346937,
            1.5959183673469388,
            1.6122448979591837,
            1.6285714285714286,
            1.6448979591836734,
            1.6612244897959183,
            1.6775510204081634,
            1.693877551020408,
            1.7102040816326531,
            1.726530612244898,
            1.7428571428571429,
            1.7591836734693878,
            1.7755102040816326,
            1.7918367346938777,
            1.8081632653061224,
            1.8244897959183675,
            1.8408163265306123,
            1.8571428571428572,
            1.873469387755102,
            1.889795918367347,
            1.906122448979592,
            1.9224489795918367,
            1.9387755102040818,
            1.9551020408163267,
            1.9714285714285715,
            1.9877551020408164,
            2.0040816326530613,
            2.0204081632653064,
            2.036734693877551,
            2.053061224489796,
            2.069387755102041,
            2.085714285714286,
            2.1020408163265305,
            2.1183673469387756,
            2.1346938775510207,
            2.1510204081632653,
            2.1673469387755104,
            2.183673469387755,
            2.2
        ]
    },
    "driver": "energy",
    "model": {
        "method": "qed-fci",
        "orbital_basis": "6-311g",
        "photon_basis": "coherent_state_basis",
        "number_of_photon_states": 10,
        "nact_orbs": 4,
        "nact_els": 4,
        "lambda": [
            0.0,
            0.0,
            0.05
        ],
        "omega": 0.12086
    },
    "return_result": [
        [
            -7.974358465285259,
            -7.8551431531449785,
            -7.8222443588507575,
            -7.812278971313897,
            -7.771000388442692,
            -7.761551807182309,
            -7.734800448907665,
            -7.701386796328962,
            -7.691200149218696,
            -7.650143260287772
        ],
        [
            -7.9754499897398565,
            -7.856312567474869,
            -7.824138635880431,
            -7.814038989681503,
            -7.772956731045352,
            -7.763463143584086,
            -7.735994746421135,
            -7.703281005766869,
            -7.692943475116878,
            -7.652099451831292
        ],
        [
            -7.976417645351011,
            -7.857362431125077,
            -7.825930987935656,
            -7.815691226152868,
            -7.77480601668037,
            -7.765267405955413,
            -7.737070955288527,
            -7.70507329267664,
            -7.694577708425922,
            -7.653948604598289
        ],
        [
            -7.977268004189211,
            -7.8582995793999295,
            -7.827626667255595,
            -7.817240686685062,
            -7.776553603648104,
            -7.7669700314376975,
            -7.738035969828162,
            -7.7067689090871605,
            -7.6961078001904335,
            -7.655696076706918
        ],
        [
            -7.978007299201127,
            -7.859130526330567,
            -7.829230653584666,
            -7.818692085004888,
            -7.778204575724284,
            -7.768576178950891,
            -7.7388963638187445,
            -7.708372834724258,
            -7.697538408166567,
            -7.657346951752943
        ],
        [
            -7.978641442653318,
            -7.859861484192081,
            -7.830747669241274,
            -7.8200498568776595,
            -7.779763757363158,
            -7.770090744679334,
            -7.73965840962944,
            -7.709889791830519,
            -7.698873912303804,
            -7.658906054010359
        ],
        [
            -7.979176043509381,
            -7.860498381991274,
            -7.83218219335759,
            -7.821318173423271,
            -7.781235728043894,
            -7.771518376676086,
            -7.740328096176595,
            -7.711324259462253,
            -7.7001184280271735,
            -7.660377962775497
        ],
        [
            -7.979616423786431,
            -7.861046882883052,
            -7.83353847500987,
            -7.822500953620365,
            -7.782624835519007,
            -7.772863488339698,
            -7.7409111456975745,
            -7.712680486621816,
            -7.701275819499612,
            -7.661767025613443
        ],
        [
            -7.979967633993816,
            -7.861512400781507,
            -7.834820546107692,
            -7.823601875895092,
            -7.783935208756415,
            -7.774130271571093,
            -7.741413029640226,
            -7.713962505146737,
            -7.702349711934285,
            -7.663077371297662
        ],
        [
            -7.9802344676542445,
            -7.861900115899897,
            -7.836032232998,
            -7.824624389092284,
            -7.785170769634265,
            -7.775322708654556,
            -7.741838983292707,
            -7.715174141313929,
            -7.703343503460934,
            -7.664312921503562
        ],
        [
            -7.980421475002947,
            -7.862214989465859,
            -7.837177167642557,
            -7.8255717227363375,
            -7.786335244178795,
            -7.776444583665305,
            -7.742194019463419,
            -7.716319027017191,
            -7.704260376418383,
            -7.665477402045219
        ],
        [
            -7.980532975897775,
            -7.862461777536401,
            -7.8382587980849525,
            -7.826446896728552,
            -7.787432173090897,
            -7.777499493145496,
            -7.742482941095438,
            -7.71740061023423,
            -7.705103308248506,
            -7.666574353542528
        ],
        [
            -7.9805730719903005,
            -7.862645043930427,
            -7.8392803983005095,
            -7.82725273055515,
            -7.7884649216435236,
            -7.778490856141231,
            -7.742710352831053,
            -7.718422164876485,
            -7.705875082069576,
            -7.6676071407887
        ],
        [
            -7.980545658202147,
            -7.8627691722705135,
            -7.840245077466118,
            -7.827991852097116,
            -7.789436689008068,
            -7.77942192363976,
            -7.742880671516121,
            -7.7193868000590635,
            -7.7065782970219745,
            -7.668578962820076
        ],
        [
            -7.980454433548188,
            -7.86283837711396,
            -7.841155788685156,
            -7.828666706140097,
            -7.790350517020245,
            -7.780295787444082,
            -7.742998135628813,
            -7.720297468825568,
            -7.707215378480243,
            -7.669492861212832
        ],
        [
            -7.9803029113451736,
            -7.862856714140764,
            -7.842015337200026,
            -7.82927956268897,
            -7.79120929843679,
            -7.781115388518987,
            -7.743066813613315,
            -7.7211569763606525,
            -7.707788588222207,
            -7.670351728456345
        ],
        [
            -7.980094428842878,
            -7.862828089355174,
            -7.842826388123756,
            -7.829832525200031,
            -7.792015784707899,
            -7.781883524841547,
            -7.743090611100034,
            -7.721967987721563,
            -7.708300034644107,
            -7.671158315699477
        ],
        [
            -7.979832156312276,
            -7.862756267257843,
            -7.843591473719902,
            -7.830327538895152,
            -7.792772593296021,
            -7.782602858786712,
            -7.74307327700004,
            -7.722733035117997,
            -7.7087516831153335,
            -7.671915240066687
        ],
        [
            -7.9795191056220265,
            -7.8626448778597045,
            -7.844313000257858,
            -7.830766399009202,
            -7.793482214569426,
            -7.783275924076278,
            -7.743018408438921,
            -7.723454524767516,
            -7.709145366463212,
            -7.672624991646232
        ],
        [
            -7.979158138336247,
            -7.862497422629387,
            -7.844993254470354,
            -7.831150759775663,
            -7.794147018295303,
            -7.783905132318785,
            -7.742929454593408,
            -7.724134743352744,
            -7.709482795842071,
            -7.673289939851658
        ],
        [
            -7.9787519733595715,
            -7.862317279092562,
            -7.8456344096369515,
            -7.831482143374467,
            -7.794769259758884,
            -7.784492779165806,
            -7.742809719369356,
            -7.724775864104982,
            -7.709765571758075,
            -7.673912339607659
        ],
        [
            -7.978303194158171,
            -7.862107704171639,
            -7.846238531316709,
            -7.831761949631598,
            -7.795351085530271,
            -7.785041050108087,
            -7.742662363019955,
            -7.725379952536843,
            -7.7099951954562895,
            -7.674494337108641
        ],
        [
            -7.977814255582033,
            -7.861871836149931,
            -7.846807582752216,
            -7.831991466306459,
            -7.795894538901957,
            -7.7855520259350515,
            -7.742490402749356,
            -7.725948971846111,
            -7.710173080572522,
            -7.675037975255166
        ],
        [
            -7.977287490312691,
            -7.861612695235466,
            -7.8473434299652824,
            -7.832171880090821,
            -7.796401565017261,
            -7.786027687878477,
            -7.742296712404082,
            -7.726484788011589,
            -7.710300565008732,
            -7.6755451987821885
        ],
        [
            -7.976725114958592,
            -7.86133318272042,
            -7.847847846563506,
            -7.832304288365018,
            -7.796874015708529,
            -7.786469922460503,
            -7.742084021388115,
            -7.726989174479956,
            -7.710378922963227,
            -7.676017859097641
        ],
        [
            -7.976129235820367,
            -7.861036078773788,
            -7.848322518276518,
            -7.832389711714256,
            -7.797313654064957,
            -7.786880526065717,
            -7.741854912955784,
            -7.727463817171379,
            -7.71040937685101,
            -7.676457718850523
        ],
        [
            -7.975501854345811,
            -7.860724038961308,
            -7.848769047239114,
            -7.8324291071507135,
            -7.79772215874553,
            -7.787261209367259,
            -7.741611822125414,
            -7.7279103180708235,
            -7.710393109285607,
            -7.676866456244273
        ],
        [
            -7.974844872293626,
            -7.860399589641615,
            -7.8491889560374455,
            -7.832423381925278,
            -7.798101128054942,
            -7.787613600954613,
            -7.741357033393266,
            -7.728330199870618,
            -7.710331274479491,
            -7.677245669113236
        ],
        [
            -7.9741600966244395,
            -7.860065122463594,
            -7.849583691533592,
            -7.83237340774092,
            -7.79845208379707,
            -7.7879392518361295,
            -7.741092678550982,
            -7.728724909121506,
            -7.710225009173844,
            -7.677596878776757
        ],
        [
            -7.973449244135293,
            -7.8597228882520485,
            -7.849954628484405,
            -7.8322800351028,
            -7.798776474920428,
            -7.788239638645414,
            -7.740820734806125,
            -7.729095820679793,
            -7.710075442730157,
            -7.6779215336834366
        ],
        [
            -7.972713945854326,
            -7.8593749906448505,
            -7.850303072966228,
            -7.83214410749429,
            -7.799075680969735,
            -7.788516167187868,
            -7.740543023591189,
            -7.729444240589185,
            -7.709883706181331,
            -7.678221012872968
        ],
        [
            -7.971955751210431,
            -7.859023379880387,
            -7.850630265620683,
            -7.8319664749794,
            -7.799351015356082,
            -7.788770175699161,
            -7.740261210145692,
            -7.729771409460312,
            -7.709650940017479,
            -7.678496629227516
        ],
        [
            -7.971176131991257,
            -7.858669847181044,
            -7.8509373847317905,
            -7.8317480068321945,
            -7.799603728457223,
            -7.789002937933165,
            -7.7399768041962025,
            -7.730078505546275,
            -7.709378300531004,
            -7.678749632593295
        ],
        [
            -7.970376486104194,
            -7.858316020176244,
            -7.851225549147574,
            -7.831489602768465,
            -7.799835010559719,
            -7.789215666092633,
            -7.7396911618490565,
            -7.730366647666204,
            -7.709066964583101,
            -7.678981212637547
        ],
        [
            -7.969558141151184,
            -7.85796335978266,
            -7.851495821055504,
            -7.831192202385507,
            -7.800045994657793,
            -7.789409513612228,
            -7.739405488805122,
            -7.730636897980486,
            -7.708718132716902,
            -7.679192502034283
        ],
        [
            -7.968722357829514,
            -7.857613158903675,
            -7.851749208622407,
            -7.830856792476911,
            -7.800237759101572,
            -7.78958557780486,
            -7.739120844925379,
            -7.7308902646290365,
            -7.708333030600534,
            -7.679384578337817
        ],
        [
            -7.967870333169436,
            -7.857266543188274,
            -7.851986668508149,
            -7.830484411953882,
            -7.8004113301339055,
            -7.789744902380976,
            -7.7388381501199595,
            -7.731127704246141,
            -7.707912908861362,
            -7.679558467301204
        ],
        [
            -7.967003203618221,
            -7.856924474069961,
            -7.852209108261488,
            -7.830076154296019,
            -7.800567684293807,
            -7.789888479849272,
            -7.738558191449691,
            -7.731350124356054,
            -7.707459041426706,
            -7.679715144890085
        ],
        [
            -7.966122047979604,
            -7.8565877540190785,
            -7.85241738860595,
            -7.829633167448327,
            -7.800707750714572,
            -7.79001725380691,
            -7.7382816312962115,
            -7.731558385658743,
            -7.70697272254657,
            -7.67985553973025
        ],
        [
            -7.965227890217825,
            -7.856257033969261,
            -7.852612325623555,
            -7.829156651346047,
            -7.800832413303745,
            -7.790132121127346,
            -7.738009016384457,
            -7.7317533042137025,
            -7.7064552627172125,
            -7.679980535012135
        ],
        [
            -7.964321702133301,
            -7.855932822664539,
            -7.8527946928424,
            -7.82864785328331,
            -7.800942512848244,
            -7.790233934051874,
            -7.737740787439899,
            -7.731935653527388,
            -7.705907983748765,
            -7.680090971001863
        ],
        [
            -7.9634044059172195,
            -7.85561549760749,
            -7.852965223234509,
            -7.828108061469037,
            -7.801038849002361,
            -7.7903235021911295,
            -7.73747728922808,
            -7.732106166551067,
            -7.705332213236346,
            -7.6801876467672825
        ],
        [
            -7.9624768765922616,
            -7.855305317215696,
            -7.853124611129849,
            -7.827538597175183,
            -7.801122182200864,
            -7.790401594443119,
            -7.737218780737402,
            -7.732265537594776,
            -7.704729278689347,
            -7.680271322156438
        ],
        [
            -7.9615399443446115,
            -7.855002433757241,
            -7.853273514050707,
            -7.826940805916525,
            -7.801193235486749,
            -7.79046894083159,
            -7.736965445276765,
            -7.732414424161733,
            -7.7041005015568516,
            -7.680342719626453
        ],
        [
            -7.960594396753086,
            -7.854706906634933,
            -7.853412554471523,
            -7.826316048103782,
            -7.801252696261432,
            -7.790526234270105,
            -7.736717400286607,
            -7.73255344870804,
            -7.703447191361778,
            -7.68040252599485
        ],
        [
            -7.959640980920395,
            -7.854418715614613,
            -7.853542321507831,
            -7.825665689583397,
            -7.801301217960996,
            -7.79057413225562,
            -7.736474706694047,
            -7.732683200331639,
            -7.702770640121948,
            -7.68045139411702
        ],
        [
            -7.958680405511323,
            -7.854137773642756,
            -7.853663372538325,
            -7.824991092427715,
            -7.801339421663705,
            -7.7906132584954655,
            -7.736237377674805,
            -7.732804236394338,
            -7.702072117200679,
            -7.680489944669276
        ],
        [
            -7.957713342701279,
            -7.853863938962053,
            -7.853776234762508,
            -7.824293606274071,
            -7.801367897625569,
            -7.790644204470469,
            -7.736005386756476,
            -7.732917084079463,
            -7.701352864682937,
            -7.680518767004412
        ],
        [
            -7.956740430039634,
            -7.853881406697078,
            -7.853597026305113,
            -7.8235745604381295,
            -7.80138720676165,
            -7.790667530937212,
            -7.735778675126298,
            -7.733022241888116,
            -7.700614093357983,
            -7.680538421631959
        ],
        [
            -7.955762272231352,
            -7.853979359613887,
            -7.853336817019664,
            -7.82283525695789,
            -7.80139788205749,
            -7.790683769372668,
            -7.7355571582201,
            -7.733120181077236,
            -7.699856979326617,
            -7.680549440980394
        ]
    ]
}