{
    "repo": {
        "repository_url": "https://github.com/mapol-chem/qed-ci",
        "branch": "direct_ci",
        "commit": "18d2b9cee4d3f5c37008da2bb7e9833f14107b67"
    },
    "molecule": {
        "molecule_name": "LiH",
        "geometry": [
            [
                0.0,
                0.0,
                -0.3398954808908949
            ],
            [
                0.0,
                0.0,
                2.3661923307647155
            ]
        ],
        "symbols": [
            "Li",
            "H"
        ],
        "z-matrix": "\n    0 1\n    Li\n    H 1 1.432\n    symmetry c1\n",
        "bond_length": 1.432
    },
    "driver": "energy",
    "model": {
        "method": "qed-fci",
        "orbital_basis": "sto-3g",
        "photon_basis": "number_basis",
        "number_of_photon_states": 9,
        "lambda": [
            0.0,
            0.0,
            0.05
        ],
        "omega": 0.12086
    },
    "return_result": [
        -7.876697278753612,
        -7.758661001363662,
        -7.750842586601659,
        -7.731769585725405,
        -7.704197956301859,
        -7.704197956297859,
        -7.681247032513118
    ],
    "cavity_free_rhf_energy": -7.861989570293467,
    "qed_rhf_energy": -7.858066222761357,
    "cavity_free_fci_ground_state_energy": -7.88021385504503
}