{
    "repo": {
        "repository_url": "https://github.com/mapol-chem/qed-ci",
        "branch": "coherent_state_basis",
        "commit": "dd41745c62d7d377f59748cc7d6b57ee95367e00"
    },
    "molecule": {
        "molecule_name": "azobenzene",
        "geometry": [
            [
                -0.6990987512,
                -1.1271651407,
                -0.2344860629
            ],
            [
                -0.6990987512,
                -1.1271651407,
                1.1648333173
            ],
            [
                -0.6990987512,
                -2.3719602993,
                1.7925481251
            ],
            [
                -0.7777503145,
                -2.4486627117,
                3.170819362
            ],
            [
                -0.8799114625,
                -1.291105861,
                3.9338024928
            ],
            [
                -0.89348331,
                -0.0519339385,
                3.3071392938
            ],
            [
                -0.7869699096,
                0.0388465039,
                1.9297225629
            ],
            [
                -0.6536205885,
                -3.2534367543,
                1.1854941206
            ],
            [
                -0.7752540315,
                -3.4084543057,
                3.6495703842
            ],
            [
                -0.960203312,
                -1.3549621967,
                5.001370803
            ],
            [
                -0.9851100749,
                0.8437727128,
                3.8905579918
            ],
            [
                -0.808029511,
                0.9947771576,
                1.4442535032
            ],
            [
                -0.8336506934,
                -0.1709434538,
                -1.0443939922
            ],
            [
                0.1339697628,
                0.6485362598,
                -1.6363541958
            ],
            [
                -0.3055686388,
                1.5207390653,
                -2.6311427086
            ],
            [
                0.6070346164,
                2.3037470103,
                -3.3136002206
            ],
            [
                1.9644563542,
                2.2096364323,
                -3.0288893676
            ],
            [
                2.403110892,
                1.3308347445,
                -2.0471940005
            ],
            [
                1.4961986436,
                0.5621173856,
                -1.3376595146
            ],
            [
                -1.3517071043,
                1.5544727283,
                -2.8592650922
            ],
            [
                0.2640638885,
                2.974933326,
                -4.0766795385
            ],
            [
                2.6715316203,
                2.8043666431,
                -3.573463736
            ],
            [
                3.4508067851,
                1.2451303148,
                -1.832603468
            ],
            [
                1.835026846,
                -0.1244532345,
                -0.5868315443
            ]
        ],
        "constrained_dihedral": 180,
        "molecule_string": "0 1\n\t    N    -0.6990987512  -1.1271651407  -0.2344860629\n\t    C    -0.6990987512  -1.1271651407   1.1648333173\n\t    C    -0.6990987512  -2.3719602993   1.7925481251\n\t    C    -0.7777503145  -2.4486627117   3.1708193620\n\t    C    -0.8799114625  -1.2911058610   3.9338024928\n\t    C    -0.8934833100  -0.0519339385   3.3071392938\n\t    C    -0.7869699096   0.0388465039   1.9297225629\n\t    H    -0.6536205885  -3.2534367543   1.1854941206\n\t    H    -0.7752540315  -3.4084543057   3.6495703842\n\t    H    -0.9602033120  -1.3549621967   5.0013708030\n\t    H    -0.9851100749   0.8437727128   3.8905579918\n\t    H    -0.8080295110   0.9947771576   1.4442535032\n\t    N    -0.8336506934  -0.1709434538  -1.0443939922\n\t    C     0.1339697628   0.6485362598  -1.6363541958\n\t    C    -0.3055686388   1.5207390653  -2.6311427086\n\t    C     0.6070346164   2.3037470103  -3.3136002206\n\t    C     1.9644563542   2.2096364323  -3.0288893676\n\t    C     2.4031108920   1.3308347445  -2.0471940005\n\t    C     1.4961986436   0.5621173856  -1.3376595146\n\t    H    -1.3517071043   1.5544727283  -2.8592650922\n\t    H     0.2640638885   2.9749333260  -4.0766795385\n\t    H     2.6715316203   2.8043666431  -3.5734637360\n\t    H     3.4508067851   1.2451303148  -1.8326034680\n\t    H     1.8350268460  -0.1244532345  -0.5868315443\nsymmetry c1",
        "symbols": [
            "N",
            "C",
            "C",
            "C",
            "C",
            "C",
            "C",
            "H",
            "H",
            "H",
            "H",
            "H",
            "N",
            "C",
            "C",
            "C",
            "C",
            "C",
            "C",
            "H",
            "H",
            "H",
            "H",
            "H"
        ]
    },
    "driver": "energy",
    "model": {
        "method": "qed-casci",
        "orbital_basis": "6-31G",
        "photon_basis": "number_basis",
        "active_orbitals": 6,
        "active_electrons": 6,
        "number_of_photon_states": 1,
        "lambda": [
            0.0,
            0.0,
            0.01
        ],
        "omega": 0.0477741
    },
    "return_result": [],
    "cavity_free_rhf_energy": -568.77444887865,
    "qed_rhf_energy": 0.0,
    "cavity_free_fci_ground_state_energy": 0.0,
    "constrained_dihedral": 90.9999999999
}