{
    "molecule": {
        "molecule_name": "HHe+",
        "geometry": [
            "\nH       \nHE            1    0.776011\n1 1\nsymmetry c1\n"
        ],
        "symbols": [
            "H",
            "He"
        ],
        "basis_set": "cc-pVTZ"
    },
    "coupling data": [
        [
            0.0,
            0.0,
            0.0
        ],
        [
            0.0,
            0.0,
            0.001
        ],
        [
            0.0,
            0.0,
            0.002
        ],
        [
            0.0,
            0.0,
            0.003
        ],
        [
            0.0,
            0.0,
            0.004
        ],
        [
            0.0,
            0.0,
            0.005
        ],
        [
            0.0,
            0.0,
            0.006
        ],
        [
            0.0,
            0.0,
            0.007
        ],
        [
            0.0,
            0.0,
            0.008
        ],
        [
            0.0,
            0.0,
            0.009
        ],
        [
            0.0,
            0.0,
            0.01
        ],
        [
            0.0,
            0.0,
            0.011
        ],
        [
            0.0,
            0.0,
            0.012
        ],
        [
            0.0,
            0.0,
            0.013
        ],
        [
            0.0,
            0.0,
            0.014
        ],
        [
            0.0,
            0.0,
            0.015
        ],
        [
            0.0,
            0.0,
            0.016
        ],
        [
            0.0,
            0.0,
            0.017
        ],
        [
            0.0,
            0.0,
            0.018
        ],
        [
            0.0,
            0.0,
            0.019
        ],
        [
            0.0,
            0.0,
            0.02
        ],
        [
            0.0,
            0.0,
            0.025
        ],
        [
            0.0,
            0.0,
            0.03
        ],
        [
            0.0,
            0.0,
            0.035
        ],
        [
            0.0,
            0.0,
            0.04
        ],
        [
            0.0,
            0.0,
            0.045
        ],
        [
            0.0,
            0.0,
            0.05
        ],
        [
            0.0,
            0.0,
            0.055
        ],
        [
            0.0,
            0.0,
            0.06
        ],
        [
            0.0,
            0.0,
            0.065
        ],
        [
            0.0,
            0.0,
            0.07
        ],
        [
            0.0,
            0.0,
            0.075
        ],
        [
            0.0,
            0.0,
            0.08
        ],
        [
            0.0,
            0.0,
            0.085
        ],
        [
            0.0,
            0.0,
            0.09
        ],
        [
            0.0,
            0.0,
            0.095
        ],
        [
            0.0,
            0.0,
            0.1
        ]
    ],
    "omega": 0.9654959009,
    "energy_data": {
        "pt2_pn": {
            "method": "second order perturbation theory",
            "number of states included": 60,
            "photon_basis": "photon_number_basis",
            "energies": [
                -2.9751856590384476,
                -2.9751854389975483,
                -2.9751847788795884,
                -2.9751836786987838,
                -2.9751821384788273,
                -2.9751801582528885,
                -2.9751777380636146,
                -2.9751748779631284,
                -2.9751715780130317,
                -2.9751678382844027,
                -2.975163658857795,
                -2.975159039823243,
                -2.975153981280254,
                -2.975148483337815,
                -2.975142546114389,
                -2.9751361697379175,
                -2.9751293543458166,
                -2.975122100084981,
                -2.975114407111783,
                -2.975106275592071,
                -2.9750977057011703,
                -2.9750482874786375,
                -2.9749879417245664,
                -2.9749167010163733,
                -2.9748346038546396,
                -2.974741694663113,
                -2.9746380237887085,
                -2.9745236475015067,
                -2.974398627994755,
                -2.974263033384867,
                -2.974116937711423,
                -2.9739604209371695,
                -2.973793568948019,
                -2.9736164735530513,
                -2.973429232484512,
                -2.973231949397813,
                -2.9730247338715334
            ]
        },
        "pt3_pn": {
            "method": "third order perturbation theory",
            "number of states included": 60,
            "photon_basis": "photon_number_basis",
            "energies": [
                -2.9751856590384476,
                -2.97518543899682,
                -2.975184778867935,
                -2.9751836786397874,
                -2.9751821382923693,
                -2.9751801577976664,
                -2.9751777371196604,
                -2.975174876214324,
                -2.9751715750296244,
                -2.9751678335055165,
                -2.9751636515739417,
                -2.97515902915883,
                -2.9751539661760904,
                -2.975148462533612,
                -2.975142518131262,
                -2.9751361328608765,
                -2.9751293066062625,
                -2.9751220392431907,
                -2.9751143306393915,
                -2.975106180654551,
                -2.9750975891403035,
                -2.9750480028710333,
                -2.9749873514730876,
                -2.9749156073074468,
                -2.9748327376512793,
                -2.9747387046686775,
                -2.974633465376889,
                -2.9745169716080433,
                -2.974389169966381,
                -2.974250001780972,
                -2.974099403053941,
                -2.973937304404183,
                -2.9737636310065803,
                -2.9735783025267137,
                -2.973381233051076,
                -2.9731723310127776,
                -2.972951499112752
            ]
        },
        "pt2_cs": {
            "method": "second order perturbation theory",
            "number of states included": 60,
            "photon_basis": "coherent_state_basis",
            "energies": [
                -2.9751856590384476,
                -2.9751854389973564,
                -2.9751847788765167,
                -2.975183678683233,
                -2.975182138429679,
                -2.9751801581328974,
                -2.975177737814801,
                -2.975174877502171,
                -2.9751715772266594,
                -2.9751678370247854,
                -2.9751636569379403,
                -2.9751590370123826,
                -2.975153977299242,
                -2.975148477854516,
                -2.975142538739073,
                -2.975136160018649,
                -2.975129341763852,
                -2.975122084050157,
                -2.9751143869579093,
                -2.975106250572323,
                -2.975097674983484,
                -2.975048212484285,
                -2.9749877862162775,
                -2.9749164129180694,
                -2.974834112371653,
                -2.9747409074024014,
                -2.9746368238790737,
                -2.97452189071381,
                -2.974396139862136,
                -2.9742596063229585,
                -2.9741123281385695,
                -2.9739543463946423,
                -2.9737857052202354,
                -2.9736064517877887,
                -2.9734166363131274,
                -2.9732163120554587,
                -2.973005535317373
            ]
        },
        "pt3_cs": {
            "method": "third order perturbation theory",
            "number of states included": 60,
            "photon_basis": "coherent_state_basis",
            "energies": [
                -2.9751856590384476,
                -2.9751854389970553,
                -2.975184778871697,
                -2.975183678658834,
                -2.9751821383525656,
                -2.9751801579446306,
                -2.9751777374244073,
                -2.975174876778909,
                -2.975171575992789,
                -2.9751678350483313,
                -2.9751636539254576,
                -2.9751590326017188,
                -2.9751539710522965,
                -2.975148469249999,
                -2.975142527165262,
                -2.9751361447661413,
                -2.975129322018314,
                -2.975122058885074,
                -2.9751143553273285,
                -2.975106211303594,
                -2.9750976267699967,
                -2.975048094750368,
                -2.974987542019342,
                -2.9749159603732234,
                -2.974833340074792,
                -2.974739669832328,
                -2.9746349367754155,
                -2.9745191264275124,
                -2.974392222675305,
                -2.9742542077348206,
                -2.9741050621143317,
                -2.9739447645740147,
                -2.9737732920823987,
                -2.973590619769576,
                -2.9733967208771936,
                -2.9731915667052142,
                -2.97297512655545
            ]
        },
        "PCQED_gs": {
            "method": "PCQED",
            "number of states included": 60,
            "photon_basis": "photon_number_basis",
            "energies": [
                -2.9751856590384476,
                -2.9751854389971744,
                -2.9751847788736674,
                -2.97518367866879,
                -2.975182138384036,
                -2.9751801580214536,
                -2.9751777375837114,
                -2.9751748770740525,
                -2.975171576496313,
                -2.975167835854899,
                -2.9751636551548537,
                -2.9751590344017607,
                -2.9751539736018278,
                -2.975148472761838,
                -2.9751425318891482,
                -2.9751361509917396,
                -2.975129330078153,
                -2.9751220691575426,
                -2.975114368239636,
                -2.9751062273347566,
                -2.9750976464538095,
                -2.975048142831222,
                -2.974987641782344,
                -2.974916145333408,
                -2.9748336558782005,
                -2.9747401761775754,
                -2.974635709358949,
                -2.9745202589157365,
                -2.9743938287067,
                -2.9742564229552335,
                -2.9741080462485825,
                -2.9739487035369825,
                -2.9737784001328325,
                -2.973597141709605,
                -2.9734049343008806,
                -2.973201784299227,
                -2.9729876984550225
            ]
        }
    }
}