{
    "repo": {
        "repository_url": "https://github.com/mapol-chem/qed-ci",
        "branch": "direct_ci",
        "commit": "7f25d1c5fd458a06002e79d610aa17399f213f71"
    },
    "molecule": {
        "molecule_name": "H2O+",
        "geometry": [
            [
                [
                    0.0,
                    0.0,
                    -0.1294768896666024
                ],
                [
                    0.0,
                    -1.4941867446311508,
                    1.0274460988722685
                ],
                [
                    0.0,
                    1.4941867446311508,
                    1.0274460988722685
                ]
            ],
            [
                [
                    0.0,
                    0.0,
                    1.7602492357912258
                ],
                [
                    0.0,
                    -1.4941867446311508,
                    2.9171722243300966
                ],
                [
                    0.0,
                    1.4941867446311508,
                    2.9171722243300966
                ]
            ],
            [
                [
                    0.0,
                    0.0,
                    3.6499753612490538
                ],
                [
                    0.0,
                    -1.4941867446311508,
                    4.806898349787925
                ],
                [
                    0.0,
                    1.4941867446311508,
                    4.806898349787925
                ]
            ],
            [
                [
                    0.0,
                    0.0,
                    5.539701486706882
                ],
                [
                    0.0,
                    -1.4941867446311508,
                    6.696624475245753
                ],
                [
                    0.0,
                    1.4941867446311508,
                    6.696624475245753
                ]
            ],
            [
                [
                    0.0,
                    0.0,
                    7.42942761216471
                ],
                [
                    0.0,
                    -1.4941867446311508,
                    8.58635060070358
                ],
                [
                    0.0,
                    1.4941867446311508,
                    8.58635060070358
                ]
            ],
            [
                [
                    0.0,
                    0.0,
                    9.319153737622537
                ],
                [
                    0.0,
                    -1.4941867446311508,
                    10.47607672616141
                ],
                [
                    0.0,
                    1.4941867446311508,
                    10.47607672616141
                ]
            ],
            [
                [
                    0.0,
                    0.0,
                    11.208879863080366
                ],
                [
                    0.0,
                    -1.4941867446311508,
                    12.365802851619236
                ],
                [
                    0.0,
                    1.4941867446311508,
                    12.365802851619236
                ]
            ],
            [
                [
                    0.0,
                    0.0,
                    13.098605988538194
                ],
                [
                    0.0,
                    -1.4941867446311508,
                    14.255528977077065
                ],
                [
                    0.0,
                    1.4941867446311508,
                    14.255528977077065
                ]
            ],
            [
                [
                    0.0,
                    0.0,
                    14.988332113996023
                ],
                [
                    0.0,
                    -1.4941867446311508,
                    16.145255102534893
                ],
                [
                    0.0,
                    1.4941867446311508,
                    16.145255102534893
                ]
            ],
            [
                [
                    0.0,
                    0.0,
                    16.878058239453853
                ],
                [
                    0.0,
                    -1.4941867446311508,
                    18.03498122799272
                ],
                [
                    0.0,
                    1.4941867446311508,
                    18.03498122799272
                ]
            ],
            [
                [
                    0.0,
                    0.0,
                    18.76778436491168
                ],
                [
                    0.0,
                    -1.4941867446311508,
                    19.92470735345055
                ],
                [
                    0.0,
                    1.4941867446311508,
                    19.92470735345055
                ]
            ],
            [
                [
                    0.0,
                    0.0,
                    20.657510490369507
                ],
                [
                    0.0,
                    -1.4941867446311508,
                    21.814433478908377
                ],
                [
                    0.0,
                    1.4941867446311508,
                    21.814433478908377
                ]
            ],
            [
                [
                    0.0,
                    0.0,
                    22.547236615827337
                ],
                [
                    0.0,
                    -1.4941867446311508,
                    23.704159604366204
                ],
                [
                    0.0,
                    1.4941867446311508,
                    23.704159604366204
                ]
            ],
            [
                [
                    0.0,
                    0.0,
                    24.436962741285164
                ],
                [
                    0.0,
                    -1.4941867446311508,
                    25.593885729824034
                ],
                [
                    0.0,
                    1.4941867446311508,
                    25.593885729824034
                ]
            ],
            [
                [
                    0.0,
                    0.0,
                    26.326688866742995
                ],
                [
                    0.0,
                    -1.4941867446311508,
                    27.48361185528186
                ],
                [
                    0.0,
                    1.4941867446311508,
                    27.48361185528186
                ]
            ],
            [
                [
                    0.0,
                    0.0,
                    28.21641499220082
                ],
                [
                    0.0,
                    -1.4941867446311508,
                    29.37333798073969
                ],
                [
                    0.0,
                    1.4941867446311508,
                    29.37333798073969
                ]
            ],
            [
                [
                    0.0,
                    0.0,
                    30.106141117658648
                ],
                [
                    0.0,
                    -1.4941867446311508,
                    31.263064106197522
                ],
                [
                    0.0,
                    1.4941867446311508,
                    31.263064106197522
                ]
            ],
            [
                [
                    0.0,
                    0.0,
                    31.99586724311648
                ],
                [
                    0.0,
                    -1.4941867446311508,
                    33.15279023165535
                ],
                [
                    0.0,
                    1.4941867446311508,
                    33.15279023165535
                ]
            ],
            [
                [
                    0.0,
                    0.0,
                    33.885593368574305
                ],
                [
                    0.0,
                    -1.4941867446311508,
                    35.04251635711318
                ],
                [
                    0.0,
                    1.4941867446311508,
                    35.04251635711318
                ]
            ],
            [
                [
                    0.0,
                    0.0,
                    35.77531949403213
                ],
                [
                    0.0,
                    -1.4941867446311508,
                    36.932242482571006
                ],
                [
                    0.0,
                    1.4941867446311508,
                    36.932242482571006
                ]
            ],
            [
                [
                    0.0,
                    0.0,
                    37.66504561948996
                ],
                [
                    0.0,
                    -1.4941867446311508,
                    38.82196860802883
                ],
                [
                    0.0,
                    1.4941867446311508,
                    38.82196860802883
                ]
            ]
        ],
        "symbols": [
            "O",
            "H",
            "H"
        ],
        "bond_length": [
            0.0,
            1.0,
            2.0,
            3.0,
            4.0,
            5.0,
            6.0,
            7.0,
            8.0,
            9.0,
            10.0,
            11.0,
            12.0,
            13.0,
            14.0,
            15.0,
            16.0,
            17.0,
            18.0,
            19.0,
            20.0
        ]
    },
    "driver": "energy",
    "model": {
        "method": "qed-cas",
        "orbital_basis": "6-31G",
        "photon_basis": "photon_number_basis",
        "number_of_photon_states": 1,
        "nact_orbs": 11,
        "nact_els": 6,
        "lambda": [
            0.0,
            0.0,
            0.01
        ],
        "omega": 0.36749303600696764
    },
    "return_result": [
        [
            -74.70899653243553,
            -74.64554893232713,
            -74.59881379800024,
            -74.53838854350731
        ],
        [
            -74.70899271164134,
            -74.64554426952007,
            -74.5988096083436,
            -74.53838297798202
        ],
        [
            -74.70895960012278,
            -74.64550742562517,
            -74.59877483025285,
            -74.53834234744964
        ],
        [
            -74.70884242173972,
            -74.64538172814682,
            -74.5986538210354,
            -74.53820817508759
        ],
        [
            -74.70856232106853,
            -74.64508689839609,
            -74.5983670729153,
            -74.53789883806361
        ],
        [
            -74.70802367634609,
            -74.64452642539989,
            -74.59781855457202,
            -74.53731699456497
        ],
        [
            -74.70712164460794,
            -74.64359508125193,
            -74.5969032434041,
            -74.53635706634049
        ],
        [
            -74.70574883186008,
            -74.64218550171405,
            -74.5955137553097,
            -74.53491173126407
        ],
        [
            -74.703800473567,
            -74.64019325265265,
            -74.59354547339188,
            -74.53287687993577
        ],
        [
            -74.70117797587275,
            -74.63752026052495,
            -74.59090003869012,
            -74.53015494064506
        ],
        [
            -74.69779098399228,
            -74.63407678878966,
            -74.58748737656852,
            -74.52665676892151
        ],
        [
            -74.69355829386473,
            -74.62978228170579,
            -74.5832265773011,
            -74.52230242752819
        ],
        [
            -74.6884079486054,
            -74.62456541560421,
            -74.57804597180494,
            -74.51702119549576
        ],
        [
            -74.68227681762586,
            -74.61836365115435,
            -74.57188269841352,
            -74.51075109542589
        ],
        [
            -74.67510988718054,
            -74.61112251037522,
            -74.56468198717577,
            -74.50343815804506
        ],
        [
            -74.6668594224332,
            -74.60279473404722,
            -74.55639631972608,
            -74.49503557548005
        ],
        [
            -74.65748410415128,
            -74.59333941935968,
            -74.54698456644147,
            -74.48550283993252
        ],
        [
            -74.64694820161185,
            -74.58272119663188,
            -74.53641116095731,
            -74.47480492406436
        ],
        [
            -74.63522081344365,
            -74.57090947560296,
            -74.5246453435566,
            -74.46291153268355
        ],
        [
            -74.62227519040745,
            -74.55787777408842,
            -74.51166048658433,
            -74.4497964368514
        ],
        [
            -74.60808814230394,
            -74.54360313063405,
            -74.49743350397945,
            -74.43543689204611
        ]
    ]
}
